README.md
requirements.txt
setup.py
bin/apk_tools_version.py
bin/bsc.py
bin/bscd.py
bin/check_mutually_exclusive_params.py
bin/check_redis.py
bin/check_wpa_passphrase.py
bin/depend_on.py
bin/du.py
bin/image_attrs.py
bin/preprocessor.py
bin/render.py
bin/wget.py
pieman/__init__.py
pieman/attrs.py
pieman/build_status_codes
pieman/codes.py
pieman/preprocessor.py
pieman/prop.py
pieman/util.py
pieman.egg-info/PKG-INFO
pieman.egg-info/SOURCES.txt
pieman.egg-info/dependency_links.txt
pieman.egg-info/requires.txt
pieman.egg-info/top_level.txt