Metadata-Version: 1.2
Name: pieman
Version: 0.19.0
Summary: Pieman package
Home-page: https://github.com/tolstoyevsky/pieman
Author: Evgeny Golyshev
Maintainer: Evgeny Golyshev
Maintainer-email: eugulixes@gmail.com
License: https://gnu.org/licenses/gpl-3.0.txt
Platform: UNKNOWN
